Metadata-Version: 2.4
Name: autodoc-ai-cli
Version: 0.1.0
Summary: An AI-powered tool to automatically document, refactor, and format Python code.
Author-email: Nirajan Paudel <nirajanpaudel33@gmail.com>
Classifier: Programming Language :: Python :: 3
Classifier: License :: OSI Approved :: MIT License
Classifier: Operating System :: OS Independent
Requires-Python: >=3.9
Requires-Dist: groq
Requires-Dist: python-dotenv
Requires-Dist: pathspec
Requires-Dist: GitPython
Requires-Dist: tomli; python_version < "3.11"
Requires-Dist: black
